MeCab.py
_MeCab.cpython-38-x86_64-linux-gnu.so
mecab.libs/libmecab-86e8f99f.so.2.0.2
mecab-0.996.13.dist-info/AUTHORS
mecab-0.996.13.dist-info/COPYING
mecab-0.996.13.dist-info/METADATA
mecab-0.996.13.dist-info/WHEEL
mecab-0.996.13.dist-info/top_level.txt
mecab-0.996.13.dist-info/RECORD
